sharepoint_manager/__init__.py
sharepoint_manager/core.py
sharepoint_manager/dataclasses.py
sharepoint_manager/decorators.py
sharepoint_manager/exceptions.py
sharepoint_manager/utils.py
sharepoint_manager-0.0.4.dist-info/licenses/LICENSE
sharepoint_manager-0.0.4.dist-info/METADATA
sharepoint_manager-0.0.4.dist-info/WHEEL
sharepoint_manager-0.0.4.dist-info/top_level.txt
sharepoint_manager-0.0.4.dist-info/RECORD
