Metadata-Version: 2.4
Name: sharepoint_manager
Version: 0.0.4
Summary: Library for interacting with sharepoint using Microsoft Graph API
Home-page: https://github.com/VBenevides/sharepoint_manager
Author: Vinicius Benevides
Author-email: viniciusm.benevides@gmail.com
License: MIT
License-File: LICENSE
Requires-Dist: msal
Dynamic: author
Dynamic: author-email
Dynamic: home-page
Dynamic: license
Dynamic: license-file
Dynamic: requires-dist
Dynamic: summary
